pesel_utils/__init__.py
pesel_utils-1.0.dist-info/METADATA
pesel_utils-1.0.dist-info/WHEEL
pesel_utils-1.0.dist-info/top_level.txt
pesel_utils-1.0.dist-info/RECORD
