Metadata-Version: 2.1
Name: pesel-utils
Version: 1.0
Summary: Utilities for checking PESEL numbers
Home-page: https://github.com/queereen/pesel_utils
Author: Avis Drożniak
Author-email: queereen@riseup.net
License: Hippocratic License 2.1
Platform: UNKNOWN
Requires-Dist: numpy
